qwed_infra/__init__.py
qwed_infra/guards/cost_guard.py
qwed_infra/guards/iam_guard.py
qwed_infra/guards/network_guard.py
qwed_infra/parsers/terraform_parser.py
qwed_infra-0.1.0.dist-info/METADATA
qwed_infra-0.1.0.dist-info/WHEEL
qwed_infra-0.1.0.dist-info/licenses/LICENSE
qwed_infra-0.1.0.dist-info/RECORD
