Metadata-Version: 2.4
Name: qwed-infra
Version: 0.1.0
Summary: Deterministic Verification for Infrastructure as Code (IaC) using Z3 and Graph Theory.
Author-email: QWED Team <rahul@qwedai.com>
License: Apache-2.0
License-File: LICENSE
Requires-Python: >=3.10
Requires-Dist: networkx>=3.0
Requires-Dist: pydantic>=2.0.0
Requires-Dist: python-hcl2>=4.3.0
Requires-Dist: requests>=2.31.0
Requires-Dist: z3-solver>=4.12.0
Provides-Extra: dev
Requires-Dist: black>=23.0.0; extra == 'dev'
Requires-Dist: pytest-cov>=4.1.0; extra == 'dev'
Requires-Dist: pytest>=7.0.0; extra == 'dev'
